dvu/__init__.py
dvu/dvu.py
dvu-0.0.2.dist-info/LICENSE
dvu-0.0.2.dist-info/METADATA
dvu-0.0.2.dist-info/WHEEL
dvu-0.0.2.dist-info/top_level.txt
dvu-0.0.2.dist-info/RECORD
