Metadata-Version: 2.1
Name: dvu
Version: 0.0.2
Summary: Functions for data visualization in matplotlib.
Home-page: https://github.com/csinva/data-viz-utils
Author: Chandan Singh
Author-email: chandan_singh@berkeley.edu
Classifier: Programming Language :: Python :: 3
Classifier: License :: OSI Approved :: MIT License
Classifier: Operating System :: OS Independent
Requires-Python: >=3.6
License-File: LICENSE
Requires-Dist: numpy
Requires-Dist: matplotlib
Requires-Dist: seaborn
Requires-Dist: scikit-learn (>=0.23.0)
Requires-Dist: adjustText
